pyclm/monitoring/__about__.py
pyclm/monitoring/__init__.py
python_yandex_cloud_monitoring-1.0.1.dist-info/licenses/LICENSE
python_yandex_cloud_monitoring-1.0.1.dist-info/METADATA
python_yandex_cloud_monitoring-1.0.1.dist-info/WHEEL
python_yandex_cloud_monitoring-1.0.1.dist-info/top_level.txt
python_yandex_cloud_monitoring-1.0.1.dist-info/RECORD
