Metadata-Version: 2.4
Name: python-yandex-cloud-monitoring
Version: 1.0.1
Summary: Python Client for Yandex Cloud Monitoring
Home-page: https://github.com/mcode-cc/python-yandex-cloud-monitoring
Author: MCode GmbH
Author-email: monitoring.pyclm@mcode.cc
License: GPLv3
Project-URL: Bug Tracker, https://github.com/mcode-cc/python-yandex-cloud-monitoring/issues
Keywords: yandex cloud monitoring trace
Platform: Any
Classifier: License :: OSI Approved :: GNU Affero General Public License v3
Classifier: Development Status :: 3 - Alpha
Classifier: Environment :: No Input/Output (Daemon)
Classifier: Environment :: Console
Classifier: Intended Audience :: Developers
Classifier: Operating System :: OS Independent
Classifier: Programming Language :: Python :: 3.9
Classifier: Programming Language :: Python :: 3.10
Classifier: Programming Language :: Python :: 3.11
Classifier: Programming Language :: Python :: 3.12
Classifier: Programming Language :: Python :: Implementation :: CPython
Classifier: Programming Language :: Python :: Implementation :: PyPy
Classifier: Topic :: Internet
Classifier: Topic :: Communications
Classifier: Topic :: Software Development :: Libraries
Classifier: Topic :: System :: Networking
Requires-Python: >=3.9
License-File: LICENSE
Requires-Dist: PyJWT>=2.4.0
Requires-Dist: requests>=2.26.0
Requires-Dist: cryptography>=3.2
Dynamic: author
Dynamic: author-email
Dynamic: classifier
Dynamic: description
Dynamic: description-content-type
Dynamic: home-page
Dynamic: keywords
Dynamic: license
Dynamic: license-file
Dynamic: platform
Dynamic: project-url
Dynamic: requires-dist
Dynamic: requires-python
Dynamic: summary
